pyxtxt/__init__.py
pyxtxt/core.py
pyxtxt/examples.py
pyxtxt/pyxtxt.py
pyxtxt/estrattori/__init__.py
pyxtxt/estrattori/audio.py
pyxtxt/estrattori/doc.py
pyxtxt/estrattori/docx.py
pyxtxt/estrattori/eml.py
pyxtxt/estrattori/epub.py
pyxtxt/estrattori/html.py
pyxtxt/estrattori/md.py
pyxtxt/estrattori/msg.py
pyxtxt/estrattori/ocr.py
pyxtxt/estrattori/ocr_ollama.py
pyxtxt/estrattori/odt.py
pyxtxt/estrattori/pdf.py
pyxtxt/estrattori/pptx.py
pyxtxt/estrattori/rtf.py
pyxtxt/estrattori/svg.py
pyxtxt/estrattori/tex.py
pyxtxt/estrattori/txt.py
pyxtxt/estrattori/xls.py
pyxtxt/estrattori/xlsx.py
pyxtxt/estrattori/xml.py
pyxtxt-0.3.4.2.dist-info/licenses/LICENSE
pyxtxt-0.3.4.2.dist-info/METADATA
pyxtxt-0.3.4.2.dist-info/WHEEL
pyxtxt-0.3.4.2.dist-info/top_level.txt
pyxtxt-0.3.4.2.dist-info/RECORD
