Metadata-Version: 2.4
Name: pyxtxt
Version: 0.3.4.2
Summary: A Python library for extracting text from different types of files (PDF, DOCX, PPTX, XLSX, ODT, ecc.).
Author-email: Giuseppe Levi <giuseppe.levi@gmail.com>
License: MIT License
Classifier: Development Status :: 4 - Beta
Classifier: Intended Audience :: Developers
Classifier: License :: OSI Approved :: MIT License
Classifier: Operating System :: OS Independent
Classifier: Programming Language :: Python :: 3
Classifier: Programming Language :: Python :: 3.7
Classifier: Programming Language :: Python :: 3.8
Classifier: Programming Language :: Python :: 3.9
Classifier: Programming Language :: Python :: 3.10
Classifier: Programming Language :: Python :: 3.11
Classifier: Topic :: Text Processing
Classifier: Topic :: Utilities
Requires-Python: >=3.7
License-File: LICENSE
Requires-Dist: python-magic; sys_platform != "win32"
Requires-Dist: python-magic-bin; sys_platform == "win32"
Provides-Extra: pdf
Requires-Dist: PyMuPDF; extra == "pdf"
Provides-Extra: docx
Requires-Dist: python-docx; extra == "docx"
Provides-Extra: presentation
Requires-Dist: python-pptx; extra == "presentation"
Provides-Extra: spreadsheet
Requires-Dist: openpyxl; extra == "spreadsheet"
Requires-Dist: xlrd; extra == "spreadsheet"
Provides-Extra: odf
Requires-Dist: odfpy; extra == "odf"
Provides-Extra: html
Requires-Dist: beautifulsoup4; extra == "html"
Requires-Dist: lxml; extra == "html"
Provides-Extra: doc
Provides-Extra: markdown
Requires-Dist: markdown; extra == "markdown"
Requires-Dist: beautifulsoup4; extra == "markdown"
Provides-Extra: epub
Requires-Dist: ebooklib; extra == "epub"
Requires-Dist: beautifulsoup4; extra == "epub"
Provides-Extra: rtf
Requires-Dist: striprtf; extra == "rtf"
Provides-Extra: email
Requires-Dist: beautifulsoup4; extra == "email"
Provides-Extra: outlook
Requires-Dist: extract-msg; extra == "outlook"
Requires-Dist: beautifulsoup4; extra == "outlook"
Provides-Extra: latex
Requires-Dist: pylatexenc; extra == "latex"
Provides-Extra: audio
Requires-Dist: openai-whisper; extra == "audio"
Provides-Extra: ocr
Requires-Dist: easyocr; extra == "ocr"
Requires-Dist: pillow; extra == "ocr"
Provides-Extra: ocr-ollama
Requires-Dist: ollama; extra == "ocr-ollama"
Requires-Dist: pillow; extra == "ocr-ollama"
Provides-Extra: all
Requires-Dist: PyMuPDF; extra == "all"
Requires-Dist: python-docx; extra == "all"
Requires-Dist: python-pptx; extra == "all"
Requires-Dist: openpyxl; extra == "all"
Requires-Dist: xlrd; extra == "all"
Requires-Dist: odfpy; extra == "all"
Requires-Dist: beautifulsoup4; extra == "all"
Requires-Dist: lxml; extra == "all"
Requires-Dist: markdown; extra == "all"
Requires-Dist: ebooklib; extra == "all"
Requires-Dist: striprtf; extra == "all"
Requires-Dist: extract-msg; extra == "all"
Requires-Dist: pylatexenc; extra == "all"
Requires-Dist: openai-whisper; extra == "all"
Requires-Dist: easyocr; extra == "all"
Requires-Dist: pillow; extra == "all"
Requires-Dist: ollama; extra == "all"
Dynamic: license-file
